CHANGES.txt
LICENSE.txt
MANIFEST.in
README.txt
setup.py
src/m01/__init__.py
src/m01.form.egg-info/PKG-INFO
src/m01.form.egg-info/SOURCES.txt
src/m01.form.egg-info/dependency_links.txt
src/m01.form.egg-info/namespace_packages.txt
src/m01.form.egg-info/not-zip-safe
src/m01.form.egg-info/requires.txt
src/m01.form.egg-info/top_level.txt
src/m01/form/README.txt
src/m01/form/__init__.py
src/m01/form/configure.zcml
src/m01/form/converter.py
src/m01/form/converter.zcml
src/m01/form/tests.py